koleo/__init__.py
koleo/__main__.py
koleo/args.py
koleo/storage.py
koleo/utils.py
koleo/api/__init__.py
koleo/api/base.py
koleo/api/client.py
koleo/api/errors.py
koleo/api/logging.py
koleo/api/types.py
koleo/cli/__init__.py
koleo/cli/aliases.py
koleo/cli/base.py
koleo/cli/connections.py
koleo/cli/seats.py
koleo/cli/station_board.py
koleo/cli/stations.py
koleo/cli/train_info.py
koleo/cli/utils.py
koleo_cli-0.2.137.27.dist-info/licenses/LICENSE
koleo_cli-0.2.137.27.dist-info/METADATA
koleo_cli-0.2.137.27.dist-info/WHEEL
koleo_cli-0.2.137.27.dist-info/entry_points.txt
koleo_cli-0.2.137.27.dist-info/top_level.txt
koleo_cli-0.2.137.27.dist-info/RECORD
