Metadata-Version: 2.4
Name: koleo-cli
Version: 0.2.137.27
Summary: Koleo CLI
Home-page: https://github.com/lzgirlcat/koleo-cli
Author: Zoey !
Maintainer-email: cb98uzhd@duck.com
License: GNU General Public License v3.0
Project-URL: Source (GitHub), https://github.com/lzgirlcat/koleo-cli
Project-URL: Issue Tracker, https://github.com/lzgirlcat/koleo-cli/issues
Keywords: koleo,timetable,trains,rail,poland
Classifier: Programming Language :: Python :: 3
Classifier: Operating System :: OS Independent
Requires-Python: >=3.12
License-File: LICENSE
Requires-Dist: rich~=14.0.0
Requires-Dist: aiohttp~=3.12.13
Requires-Dist: orjson~=3.10.18
Dynamic: author
Dynamic: classifier
Dynamic: description
Dynamic: description-content-type
Dynamic: home-page
Dynamic: keywords
Dynamic: license
Dynamic: license-file
Dynamic: maintainer-email
Dynamic: project-url
Dynamic: requires-dist
Dynamic: requires-python
Dynamic: summary
